dilbert_get.py
setup.py
dilbert_get.egg-info/PKG-INFO
dilbert_get.egg-info/SOURCES.txt
dilbert_get.egg-info/dependency_links.txt
dilbert_get.egg-info/entry_points.txt
dilbert_get.egg-info/not-zip-safe
dilbert_get.egg-info/requires.txt
dilbert_get.egg-info/top_level.txt