Metadata-Version: 1.1
Name: dilbert-get
Version: 0.0.3
Summary: downloader of dilbert comics
Home-page: https://github.com/tiagocoutinho/dilbert
Author: Tiago Coutinho
Author-email: coutinhotiago@gmail.com
License: UNKNOWN
Keywords: dilbert
Platform: UNKNOWN
Classifier: Programming Language :: Python :: 2.6
Classifier: Programming Language :: Python :: 2.7
Classifier: Programming Language :: Python :: 3.4
Classifier: Programming Language :: Python :: 3.5
Classifier: Programming Language :: Python :: 3.6
